setup.cfg
setup.py
schematics_wtf/__init__.py
schematics_wtf/converter.py
schematics_wtf.egg-info/PKG-INFO
schematics_wtf.egg-info/SOURCES.txt
schematics_wtf.egg-info/dependency_links.txt
schematics_wtf.egg-info/requires.txt
schematics_wtf.egg-info/top_level.txt