Metadata-Version: 1.1
Name: schematics-wtf
Version: 0.1.5.9
Summary: Schematics Model to WTForm converter
Home-page: http://github.com/Garito/schematics-wtf
Author: Garito
Author-email: garito@gmail.com
License: BSD
Download-URL: http://pypi.python.org/pypi/dist/schematics-wtf-0.1.5.9.tar.gz
Platform: UNKNOWN
Classifier: Environment :: Other Environment
Classifier: Intended Audience :: Developers
Classifier: License :: Other/Proprietary License
Classifier: Operating System :: POSIX
Classifier: Programming Language :: Python
